cashews/__init__.py
cashews/_typing.py
cashews/cache_condition.py
cashews/commands.py
cashews/exceptions.py
cashews/formatter.py
cashews/helpers.py
cashews/key.py
cashews/key_context.py
cashews/picklers.py
cashews/py.typed
cashews/serialize.py
cashews/ttl.py
cashews/validation.py
cashews/backends/__init__.py
cashews/backends/diskcache.py
cashews/backends/interface.py
cashews/backends/memory.py
cashews/backends/transaction.py
cashews/backends/redis/__init__.py
cashews/backends/redis/backend.py
cashews/backends/redis/client.py
cashews/backends/redis/client_side.py
cashews/contrib/__init__.py
cashews/contrib/_starlette.py
cashews/contrib/fastapi.py
cashews/contrib/prometheus.py
cashews/decorators/__init__.py
cashews/decorators/bloom.py
cashews/decorators/circuit_breaker.py
cashews/decorators/locked.py
cashews/decorators/rate.py
cashews/decorators/rate_slide.py
cashews/decorators/cache/__init__.py
cashews/decorators/cache/_exception.py
cashews/decorators/cache/defaults.py
cashews/decorators/cache/early.py
cashews/decorators/cache/fail.py
cashews/decorators/cache/hit.py
cashews/decorators/cache/iterator.py
cashews/decorators/cache/simple.py
cashews/decorators/cache/soft.py
cashews/utils/__init__.py
cashews/utils/_bitarray.py
cashews/utils/_bitarray_lib.py
cashews/utils/object_size.py
cashews/utils/split_hash.py
cashews/wrapper/__init__.py
cashews/wrapper/auto_init.py
cashews/wrapper/backend_settings.py
cashews/wrapper/callback.py
cashews/wrapper/commands.py
cashews/wrapper/decorators.py
cashews/wrapper/disable_control.py
cashews/wrapper/tags.py
cashews/wrapper/time_condition.py
cashews/wrapper/transaction.py
cashews/wrapper/wrapper.py
cashews-7.4.3.dist-info/licenses/LICENSE
cashews-7.4.3.dist-info/METADATA
cashews-7.4.3.dist-info/WHEEL
cashews-7.4.3.dist-info/top_level.txt
cashews-7.4.3.dist-info/RECORD
