Metadata-Version: 2.4
Name: cashews
Version: 7.4.3
Summary: cache tools with async power
Home-page: https://github.com/Krukov/cashews/
Author: Dmitry Kryukov
Author-email: glebov.ru@gmail.com
License: MIT
Keywords: cache aio async multicache aiocache
Classifier: Development Status :: 5 - Production/Stable
Classifier: Environment :: Web Environment
Classifier: Intended Audience :: Developers
Classifier: License :: OSI Approved :: MIT License
Classifier: Operating System :: OS Independent
Classifier: Programming Language :: Python
Classifier: Programming Language :: Python :: 3
Classifier: Programming Language :: Python :: 3 :: Only
Classifier: Programming Language :: Python :: 3.9
Classifier: Programming Language :: Python :: 3.10
Classifier: Programming Language :: Python :: 3.11
Classifier: Programming Language :: Python :: 3.12
Classifier: Programming Language :: Python :: 3.13
Requires-Python: >=3.9
License-File: LICENSE
Provides-Extra: redis
Requires-Dist: redis!=5.0.1,>=4.3.1; extra == "redis"
Provides-Extra: diskcache
Requires-Dist: diskcache>=5.0.0; extra == "diskcache"
Provides-Extra: speedup
Requires-Dist: bitarray<4.0.0; extra == "speedup"
Requires-Dist: xxhash<4.0.0; extra == "speedup"
Requires-Dist: hiredis; extra == "speedup"
Provides-Extra: dill
Requires-Dist: dill; extra == "dill"
Provides-Extra: lint
Requires-Dist: mypy>=1.5.0; extra == "lint"
Requires-Dist: types-redis; extra == "lint"
Provides-Extra: tests
Requires-Dist: pytest==8.4.2; extra == "tests"
Requires-Dist: pytest-asyncio==1.1.0; extra == "tests"
Requires-Dist: pytest-cov==6.2.1; extra == "tests"
Requires-Dist: pytest-randomly==3.16.0; extra == "tests"
Requires-Dist: pytest-rerunfailures==16.0.1; extra == "tests"
Requires-Dist: hypothesis==6.139.2; extra == "tests"
Dynamic: license-file
